analytic_wfm/__init__.py
analytic_wfm/analytic_wfm.py
analytic_wfm/peakdetect.py
analytic_wfm/test.py
analytic_wfm-0.4.dist-info/DESCRIPTION.rst
analytic_wfm-0.4.dist-info/METADATA
analytic_wfm-0.4.dist-info/RECORD
analytic_wfm-0.4.dist-info/WHEEL
analytic_wfm-0.4.dist-info/metadata.json
analytic_wfm-0.4.dist-info/pbr.json
analytic_wfm-0.4.dist-info/top_level.txt
