Metadata-Version: 2.0
Name: analytic-wfm
Version: 0.4
Summary: peak detection algorithms
Home-page: https://gist.github.com/1178136.git
Author: None
Author-email: UNKNOWN
License: UNKNOWN
Platform: UNKNOWN
Requires-Dist: numpy
Requires-Dist: scipy
